setup.py
Products/__init__.py
Products.FakeZopeUser.egg-info/PKG-INFO
Products.FakeZopeUser.egg-info/SOURCES.txt
Products.FakeZopeUser.egg-info/dependency_links.txt
Products.FakeZopeUser.egg-info/entry_points.txt
Products.FakeZopeUser.egg-info/namespace_packages.txt
Products.FakeZopeUser.egg-info/not-zip-safe
Products.FakeZopeUser.egg-info/requires.txt
Products.FakeZopeUser.egg-info/top_level.txt
Products/FakeZopeUser/__init__.py
Products/FakeZopeUser/changes.txt
Products/FakeZopeUser/configure.zcml
Products/FakeZopeUser/readme.txt
Products/FakeZopeUser/tests.py
Products/FakeZopeUser/zope2.py